text_console/__init__.py
text_console/__main__.py
text_console/__version__.py
text_console/history.py
text_console/text_console.py
text_console-1.0.14.dist-info/LICENSE
text_console-1.0.14.dist-info/METADATA
text_console-1.0.14.dist-info/WHEEL
text_console-1.0.14.dist-info/entry_points.txt
text_console-1.0.14.dist-info/top_level.txt
text_console-1.0.14.dist-info/RECORD
