Metadata-Version: 2.1
Name: text_console
Version: 1.0.14
Summary: ('A customizable Tkinter-based text console widget, in which a user types in commands to be sent to the Python interpreter.',)
Home-page: https://github.com/Ircama/text_console
Author: Ircama
License: EUPL-1.2
Keywords: shell console tkinter
Classifier: Programming Language :: Python :: 3
Classifier: License :: OSI Approved :: European Union Public Licence 1.2 (EUPL 1.2)
Classifier: Topic :: Software Development :: Libraries :: Python Modules
Classifier: Programming Language :: Python :: 3 :: Only
Classifier: Development Status :: 5 - Production/Stable
Classifier: Operating System :: OS Independent
Classifier: Intended Audience :: Developers
Requires-Python: >3.6
License-File: LICENSE
